pyfl/__init__.py
pyfl/accident.py
pyfl/air.py
pyfl/bikePoint.py
pyfl/cabWise.py
pyfl/client.py
pyfl/errors.py
pyfl/helper.py
pyfl/journeys.py
pyfl/mode.py
pyfl/occupancy.py
pyfl/place.py
pyfl/tube.py
pyfl-0.1.0.dist-info/LICENSE
pyfl-0.1.0.dist-info/METADATA
pyfl-0.1.0.dist-info/WHEEL
pyfl-0.1.0.dist-info/top_level.txt
pyfl-0.1.0.dist-info/RECORD
