Metadata-Version: 2.1
Name: pyfl
Version: 0.1.0
Summary: A python library that takes information from the Transport For London API
Home-page: https://github.com/wotanut/pyfl
Author: wotanut
Author-email: wotanutt@gmail.com
License: "MIT"
Project-URL: Bug Tracker, https://github.com/wotanut/pyfl/issues
Classifier: Programming Language :: Python :: 3
Classifier: License :: OSI Approved :: MIT License
Classifier: Operating System :: OS Independent
Requires-Python: >=3.6
License-File: LICENSE
